README.md
setup.py
PRakNet.egg-info/PKG-INFO
PRakNet.egg-info/SOURCES.txt
PRakNet.egg-info/dependency_links.txt
PRakNet.egg-info/top_level.txt
praknet/__init__.py
praknet/handler.py
praknet/packets.py
praknet/server.py